{
	"pressRelease":{
		"items":[

		{
				"id":"16-Leap_s",
				"published":"131212",
				"status":"latest",
				"name":"Leap/s",
				"collection":"Leap",
				"image":"XS-131211-Leap_s-01-EDIT-flat.png",
				"downloads":[
					{
       					"thumb":"xss-Leap_s(PG)Kdial029-Fi.png",
          				"tif":"Leap_s-PG-Kdial029-Fi.zip",
          				"jpg":"Leap_s(PG)case-Kdial029-Fi.jpg"
					},
					{
         				"thumb":"xss-Leap_s(PG)MOPdial030-Fi-.png",
          				"tif":"Leap_s-PG-MOPdial030-Fi.zip",
          				"jpg":"Leap_s(PG)case-MOPdial030-Fi.jpg"
					},
					{
        				"thumb":"xss-Leap_s(PG)Dia-Kdial031-Fi-.png",
          				"tif":"Leap_s-PG-Dia-Kdial031-Fi.zip",
          				"jpg":"Leap_s(PG)DiaCase-Kdial031-Fi.jpg"
					},
					{
						"thumb":"xss-Leap_s(PG)Dia-MOPdial032-Fi.png",
          				"tif":"Leap_s-PG-Dia-MOPdial032-Fi.zip",
          				"jpg":"Leap_s(PG)DiaCase-MOPdial032-Fi.jpg"
					},
					{
         				"thumb":"xss-Leap_s(ST)Kdial033-Fi.png",
          				"tif":"Leap_s-ST-Kdial033-Fi.zip",
          				"jpg":"Leap_s(ST)case-Kdial033-Fi.jpg"
					},
					{
        				"thumb":"xss-Leap_s(ST)MOPdial034-Fi.png",
          				"tif":"Leap_s-ST-MOPdial034-Fi.zip",
          				"jpg":"Leap_s(ST)case-MOPdial034-Fi.jpg"
					},
					{
						"thumb":"xss-Leap_s(ST)Dia-Kdial035-Fi.png",
          				"tif":"Leap_s-ST-DiaCase-Kdial035-Fi.zip",
          				"jpg":"Leap_s(ST)DiaCase-Kdial035-Fi.jpg"
					},
					{
						"thumb":"xss-Leap_s(ST)Dia-MOPdial036-Fi.png",
          				"tif":"dLC-Leap_s-EDIT_1136.zip",
          				"jpg":"Leap_s(ST)DiaCase-MOPdial036-Fi.jpg"
					},
					{
       					"thumb":"xss-131211-Leap_s-01-EDIT-flat-copy.png",
          				"tif":"dLC-Leap_s-persp-EDIT.zip",
          				"jpg":"131211-Leap_s-persp1-EDIT.jpg"
					},
					{
         				"thumb":"xss-131129-Leap_s_EDIT02-1133.png",
          				"tif":"dLC-Leap_s-EDIT_1136.zip",
          				"jpg":"131129-Leap_s_EDIT02-1133-flat-RGB.jpg"
					},
					{
        				"thumb":"xss-131211-Leap_s_EDIT-1088.png",
          				"tif":"dLC-Leap_s_EDIT-1088.zip",
          				"jpg":"131211-Leap_s_EDIT-1088.jpg"
					}
				],
				"texts":[
					{
						"language":"FR",
						"zip":"dLC-Leap_s-FR-txt-PR.pdf"
					},
					{
						"language":"EN",
						"zip":"dLC-Leap_s-EN-txt-PR.pdf"
					},
					{
						"language":"ES",
						"zip":"dLC-Leap_s-ES-txt-PR.pdf"
					}
				]
			},
			{
				"id":"14-City_Ego_CaractEre",
				"published":"130610",
				"status":"latest",
				"name":"City Ego Caractère",
				"collection":"City Ego",
				"image":"XS(CEC)DarkGreyPVD-flat.png",
				"downloads":[
					{
       					"thumb":"xxs_120308-CEIIC-PVD.png",
          				"tif":"CityEgoIICaractEre-PVD-TIF.zip",
          				"jpg":"120308-CityEgoIICaractEre-PVD.jpg"
					},
					{
         				"thumb":"xxs_120308-CEIIC-PVD-ST.png",
          				"tif":"CityEgoIICaractEre-PVD-ST-TIF.zip",
          				"jpg":"120308-CityEgoIICaractEre-PVD-ST.jpg"
					},
					{
        				"thumb":"xxs_120308-CEIIC-PVD-ST-RedLine.png",
          				"tif":"CityEgoIICaractEre-PVD-ST-RedLine-TIF.zip",
          				"jpg":"120308-CityEgoIICaractEre-PVD-ST-RedLine.jpg"
					},
					{
						"thumb":"xxs_120308-CEIIC-PVD-RedLine.png",
          				"tif":"CityEgoIICaractEre-PVD-RedLine-TIF.zip",
          				"jpg":"120308-CityEgoIICaractEre-PVD-RedLine.jpg"
					},
					{
        				"thumb":"xxs_120308-CEIIC-PG-RedLine.png",
          				"tif":"CityEgoIICaractEre-PG-RedLine-TIF.zip",
          				"jpg":"120308-CityEgoIICaractEre-PG-RedLine.jpg"
					},
					{
        				"thumb":"xxs_120308-CEIIC-PG-PVD.png",
          				"tif":"CityEgoIICaractEre-PG-PVD-TIF.zip",
          				"jpg":"120308-CityEgoIICaractEre-PG-PVD.jpg"
					}
					
				],
				"texts":[
					{
						"language":"FR",
						"zip":"dLC-PR-City_CaractEre-FR.zip"
					},
					{
						"language":"EN",
						"zip":"dLC-PR-City_CaractEre-EN.zip"
					},
					{
						"language":"ES",
						"zip":"dLC-PR-City_CaractEre-SP.zip"
					}
				]
			},
			{
				"id":"13-City_Ego_Episode_W",
				"published":"130605",
				"status":"latest",
				"name":"City Ego Episode W",
				"collection":"City Ego",
				"image":"xs_120308(CEE)W-diaPVD-PinkBgtte.png",
				"downloads":[
					{
       					"thumb":"xxs_120308(CEE)W-diaPVD-YellowBgtte.png",
          				"tif":"City_Ego_II_Episode_W-White-diaPVD-YellowBgtte.zip",
          				"jpg":"120308-City_Ego_II_Episode_W-White-diaPVD-YellowBgtte.jpg"
					},
					{
         				"thumb":"xxs_120308(CEE)W-diaPVD-PinkBgtte.png",
          				"tif":"City_Ego_II_Episode_W-White-diaPVD-PinkBgtte.zip",
          				"jpg":"120308-City_Ego_II_Episode_W-White-diaPVD-PinkBgtte.jpg"
					},
					{
        				"thumb":"xxs_120308(CEE)W-diaPVD-LightBlueBgtte.png",
          				"tif":"City_Ego_II_Episode_W-White-diaPVD-LightBlueBgtte.zip",
          				"jpg":"120308-City_Ego_II_Episode_White_W-diaPVD-LightBlueBgtte.jpg"
					},
					{
        				"thumb":"xxs_120308(CEE)W-dia-PVDBgtte.png",
         				"tif":"City_Ego_II_Episode_W-White-dia-PVDBgtte.zip",
          				"jpg":"120308-City_Ego_II_Episode_W-White-dia-PVDBgtte.jpg"
					},
					{
        				"thumb":"xxs_120308(CEE)W-PVDBgtte.png",
          				"tif":"City_Ego_II_Episode_W-White-PVDBgtte.zip",
          				"jpg":"120308-City_Ego_II_Episode_W-White-PVDBgtte.jpg"	
					},
					{
						"thumb":"xxs_120308(CEE)W-PVD-YellowBgtte.png",
          				"tif":"City_Ego_II_Episode_W-White-PVD-YellowBgtte.zip",
          				"jpg":"120308-City_Ego_II_Episode_W-White-PVD-YellowBgtte.jpg"
					},
					{
         				"thumb":"xxs_120308(CEE)W-PVD-PinkBgtte.png",
          				"tif":"City_Ego_II_Episode_W-White-PVD-PinkBgtte.zip",
          				"jpg":"120308-City_Ego_II_Episode_W-White-PVD-PinkBgtte.jpg"
					},
					{
					    "thumb":"xxs_120308(CEE)W-PVD-LightBlueBgtte.png",
          				"tif":"City_Ego_II_Episode_W-White-PVD-LightBlueBgtte.zip",
          				"jpg":"120308-City_Ego_II_Episode_W-White-PVD-LightBlueBgtte.jpg"
					}
				],

				"texts":[
					{
						"language":"FR",
						"zip":"dLC-PR-City_EPISODE_W-txt-FR-txt.zip"
					},
					{
						"language":"EN",
						"zip":"dLC-PR-City_EPISODE_W-txt-EN-txt.zip"
					},
					{
						"language":"ES",
						"zip":"dLC-PR-City_Episode_W-txt-SP-txt.zip"
					}
				]

			},
			{
				"id":"12-Bichrono_Rafaga",
				"published":"130522",
				"status":"latest",
				"name":"Bichrono Rafaga",
				"collection":"Bichrono",
				"image":"xs-130322(BC)RAFAGA-pers.png",
				"downloads":[
					{
       					"thumb":"xss-130322(BC)RAFAGA-pers.png",
          				"tif":"dLC(BC)Bichrono_Rafaga-pers-Ei.zip",
          				"jpg":"mail(BC)RAFAGA-Ei-CMYK.jpg"
					},
					{
         				"thumb":"xss-130213(BC)S3_Rafaga-ST.png",
          				"tif":"dLC(BC)S3_Rafaga-ST.zip",
          				"jpg":"130213(BC)S3_Rafaga-ST.jpg"
					},
					{
        				"thumb":"xss-130213(BC)S3_Rafaga-ST-diam.png",
          				"tif":"dLC(BC)S3_Rafaga-ST-diam.zip",
          				"jpg":"130213(BC)S3_Rafaga-ST-diam.jpg"
					},
					{
        				"thumb":"xss-130213(BC)S3_Rafaga-PG.png",
          				"tif":"dLC(BC)S3_Rafaga-PG.zip",
          				"jpg":"130213(BC)S3_Rafaga-PG.jpg"
					},
					{
        				"thumb":"xss-130213(BC)S3_Rafaga-PG-diam.png",
          				"tif":"dLC(BC)S3_Rafaga-PG-diam.zip",
          				"jpg":"130213(BC)S3_Rafaga-PG-diam.jpg"
					}
				],

				"texts":[
					{
						"language":"FR",
						"zip":"dLC-Bichrono_Rafaga-PR-FR-txt.zip"
					},
					{
						"language":"EN",
						"zip":"dLC-Bichrono_Rafaga-PR-EN-txt.zip"
					},
					{
						"language":"ES",
						"zip":"dLC-Bichrono_Rafaga-PR-SP-txt.zip"
					}
				]

			},
			{
				"id":"04A_City_Leap_Classic",
				"published":"130227",
				"status":"library",
				"name":"City Leap Classic Baguette",
				"collection":"City Leap",
				"image":"XS(CLC)bgtte-Ei.png",
				"downloads":[
					{
       					"thumb":"Xss(CLC)bgtte-Ei.png",
          				"tif":"dLC-City_Leap_Classic-Baguette-Ei-pathxPRESS.zip",
          				"jpg":"130301(CLC)bgtte-Wbkr.jpg"
					},
					{
         				"thumb":"xxs_120308-CLC-Yellow-bgtte.png",
          				"tif":"CityLeapClassic-Yellow-bgtte-TIF.zip",
          				"jpg":"120308-CityLeapClassic-Yellow-bgtte.jpg"
					},
					{
        				"thumb":"xxs_120308-CLC-White-bgtte.png",
          				"tif":"CityLeapClassic-White-bgtte-TIF.zip",
          				"jpg":"120308-CityLeapClassic-White-bgtte.jpg"
					},
					{
        				"thumb":"xxs_120308-CLC-Red-bgtte.png",
          				"tif":"CityLeapClassic-Red-bgtte-TIF.zip",
          				"jpg":"120308-CityLeapClassic-Red-bgtte.jpg"
					},
					{
        				"thumb":"xxs_120308-CLC-Pink-bgtte.png",
          				"tif":"CityLeapClassic-Pink-bgtte-TIF.zip",
          				"jpg":"120308-CityLeapClassic-Pink-bgtte.jpg"
					},
					{
        				"thumb":"xxs_120308-CLC-LightBlue-bgtte.png",
          				"tif":"CityLeapClassic-LightBlue-bgtte-TIF.zip",
          				"jpg":"120308-CityLeapClassic-LightBlue-bgtte.jpg"
					},
					{
        				"thumb":"xxs_120308-CLC-Green-bgtteCapa-0.png",
          				"tif":"CityLeapClassic-Green-bgtte-TIF.zip",
          				"jpg":"120308-CityLeapClassic-Green-bgtte.jpg"
					}
				],

				"texts":[
					{
						"language":"FR",
						"zip":"dLC-City_Leap_Classic-PR-FR-txt.zip"
					},
					{
						"language":"EN",
						"zip":"dLC-City_Leap_Classic-PR-EN-txt.zip"
					},
					{
						"language":"ES",
						"zip":"dLC-City_Leap_Classic-PR-SP-txt.zip"
					}
				]

			},
			{
				"id":"11-City_Cadet_II_Sun_Love",
				"published":"130211",
				"status":"library",
				"name":"City Cadet II Sun and Love",
				"collection":"City Cadet",
				"image":"XS-CC-SolAmor-EiPers.png",
				"downloads":[
					{
        				"thumb":"xss-CC_SolAmor-EiPers.png",
          				"tif":"dLC-City_CadetII_SunLove-layers.zip",
          				"jpg":"City_Cadet_II_SunLove-EiPers.jpg"
					},
					{
 						"thumb":"xss-CC_SolAmor-Fi.png",
          				"tif":"dLC-City_Cadet_II_SunLove-Fi-C.zip",
          				"jpg":"130213-City_Cadet_II_SunLove-Fi-RGB-Kbk.jpg"
					}
				],

				"texts":[
					{
						"language":"FR",
						"zip":"dLC-City_Cadet_II-SoleilEtAmour-PR-FR-txt.zip"
					},
					{
						"language":"EN",
						"zip":"dLC-City_Cadet_II-SunAndLove-PR-EN-txt.zip"
					},
					{
						"language":"ES",
						"zip":"dLC-City_Cadet_II-SolyAmor-PR-SP-txt.zip"
					}
				]

			},
			{
				"id":"04C_City_Leap_Passion",
				"published":"120306",
				"status":"library",
				"name":"City Leap Passion",
				"collection":"City Leap",
				"image":"XS-City_Leap_Passion_PR-FRK.png",
				"downloads":[
					{
        				"thumb":"xss121217-City_Leap_Passion.png",
          				"tif":"dLC-City_Leap_Passion-A4-LayersRGB.zip",
          				"jpg":"121217-City_Leap_Passion.jpg"
					}
				],

				"texts":[
					{
						"language":"FR",
						"zip":"dLC-City_Leap_Passion_PR-FR-txt.zip"
					},
					{
						"language":"EN",
						"zip":"dLC-City_Leap_Passion_PR-EN-txt.zip"
					},
					{
						"language":"ES",
						"zip":"dLC-City_Leap_Passion_PR-SP-txt.zip"
					}
				]

			},
			{
				"id":"02B-City_Ego_II_Episode",
				"published":"120306",
				"status":"library",
				"name":"City Ego Episode",
				"collection":"City Ego",
				"image":"xs_121115-PR-City_Ego_Episo.png",
				"downloads":[
					{
        				"thumb":"xxs_121114-CEIIE-Ei.png",
          				"tif":"CityEgoIIEpisode-PG-RedLine-TIF.zip",
          				"jpg":"120308-City_Ego_II_Episode-PG-RedLine.jpg"
					}
				],

				"texts":[
					{
						"language":"FR",
						"zip":"dLC-PR-City_Ego_Episode-FR-txt.zip"
					},
					{
						"language":"EN",
						"zip":"dLC-PR-City_Ego_Episode-EN-txt.zip"
					},
					{
						"language":"ES",
						"zip":"dLC-PR-City_Ego_Episode-SP-txt.zip"
					}
				]

			},
			{
				"id":"04A_City_Leap_Classic",
				"published":"120306",
				"status":"library",
				"name":"City Leap Classic",
				"collection":"City Leap",
				"image":"xs_BIGi-City_Leap_Classic_P.png",
				"downloads":[
					{
       					"thumb":"xss-CLeap_C-Ei02.png",
          				"tif":"dLC-City_Leap_Classic-Ei02.zip",
          				"jpg":"mail-CLeap_C-Ei02.jpg"
					},
					{
        				"thumb":"xss-CLeap_C-Ei01.png",
          				"tif":"dLC-City_Leap_Classic-Ei01.zip",
          				"jpg":"mail-CLeap_C-Ei01.jpg"
					}
				],

				"texts":[
					{
						"language":"FR",
						"zip":"dLC-City_Leap_Classic-PR-FR-txt.zip"
					},
					{
						"language":"EN",
						"zip":"dLC-City_Leap_Classic-PR-EN-txt.zip"
					},
					{
						"language":"ES",
						"zip":"dLC-City_Leap_Classic-PR-SP-txt.zip"
					}
				]

			},
			{
				"id":"01_Bichrono_Tech",
				"published":"121018",
				"status":"library",
				"name":"Bichrono Tech",
				"collection":"Bichrono",
				"image":"xs_121018(BC)Tech-PR-Thum.png",
				"downloads":[
					{
  						"thumb":"xxs_121018(BC)Tech-Ei.png",
          				"tif":"Bichrono_Tech_Ei_TIF.zip",
          				"jpg":"121018(BC)Tech-Ei-RGB.jpg"
					},
					{
        				"thumb":"xxs_120803-BC_Tech_Fi.png",
          				"tif":"Bichrono_Tech_Fi_TIF.zip",
          				"jpg":"120803-Bichrono_Tech-Fi.jpg"
					}
				],

				"texts":[
					{
						"language":"FR",
						"zip":"BichronoTech_PR-FR-txt.zip"
					},
					{
						"language":"EN",
						"zip":"BichronoTech_PR-En-txt.zip"
					},
					{
						"language":"ES",
						"zip":"BichronoTech_PR-SP-txt.zip"
					}
				]

			},
			{
				"id":"03A-Promess_Glamour",
				"published":"120306",
				"status":"library",
				"name":"Promess Glamour Baguette",
				"collection":"Promess",
				"image":"xs_BIGi-PG-PR-EN.png",
				"downloads":[
					{
        				"thumb":"xxs_120224-PG-Green.png",
          				"tif":"Promess_Glamour-Green-TIF.zip",
          				"jpg":"120224-Promess_Glamour-Green.jpg"
					},
					{
						"thumb":"xxs_120224-PG-LightBlue-path.png",
          				"tif":"Promess_Glamour-LightBlue-TIF.zip",
          				"jpg":"120224-Promess_Glamour-LightBlue.jpg"
					},
					{
						"thumb":"xxs_120224-PG-Violet.png",
          				"tif":"Promess_Glamour-Violet-TIF.zip",
          				"jpg":"120224-Promess_Glamour-Violet.jpg"
					},
					{
        				"thumb":"xxs_120224-PG-Pink.png",
          				"tif":"Promess_Glamour-Pink-TIF.zip",
          				"jpg":"120224-Promess_Glamour-Pink.jpg"
					},
					{
						"thumb":"xxs_120224-PG-Yellow-path.png",
          				"tif":"Promess_Glamour-Yellow-TIF.zip",
          				"jpg":"120224-Promess_Glamour-Yellow.jpg"
					},
					{
						"thumb":"xxs_120224-PG-PG-Red.png",
          				"tif":"Promess_Glamour-PG+Red-TIF.zip",
          				"jpg":"120224-Promess_Glamour-PG-Red.jpg"
					},
					{
						"thumb":"xxs_120224-PG-White-path.png",
          				"tif":"Promess_Glamour-White-TIF.zip",
          				"jpg":"120224-Promess_Glamour-PG-White.jpg"
					},
					{
       					"thumb":"xxs_121011-PG-3WA.png",
          				"tif":"Promess_Glamour-3WA.zip",
          				"jpg":"121011-Promess_Glamour-3WA.jpg"
					}
				],

				"texts":[
					{
						"language":"FR",
						"zip":"dLC-Promess_Glamour-PR-txt-FR.zip"
					},
					{
						"language":"EN",
						"zip":"dLC-Promess_Glamour-PR-txt-EN.zip"
					},
					{
						"language":"ES",
						"zip":"dLC-Promess_Glamour-PR-txt-SP.zip"
					}
				]

			},
			{
				"id":"03B-Promess_Diver_Reef_Saver",
				"published":"120306",
				"status":"library",
				"name":"Promess Reef Saver",
				"collection":"Promess",
				"image":"xs_Promess_Reef_Saver-PR-EN.png",
				"downloads":[
					{
          				"thumb":"xxs_121004-PRS-Ei.png",
          				"tif":"dLC-Promess-Reef-Saver-Ei-path.zip",
          				"jpg":"mail-Promess-Reef-Saver-Wi.jpg"
					}
				],

				"texts":[
					{
						"language":"FR",
						"zip":"dLC-Promess_Reef_Saver-PR-FR-txt.zip"
					},
					{
						"language":"EN",
						"zip":"dLC-Promess_Reef_Saver-PR-EN-txt.zip"
					},
					{
						"language":"ES",
						"zip":"dLC-Promess_Reef_Saver-PR-SP-txt.zip"
					}
				]

			},
			{
				"id":"09-Press_Release-Bichrono_Tech",
				"published":"120810",
				"status":"library",
				"name":"Bichrono Tech",
				"collection":"Bichrono",
				"image":"xs120807BiT-dLC-Bichrono_Te.jpg",
				"downloads":[
					{
        				"thumb":"xssBICRHONO_Tech.jpg",
          				"tif":"dLC-BICRHONO_Tech-design.zip",
          				"jpg":"Wi-ilBICRHONO_Tech.jpg"
					},
					{
						"thumb":"xssBichronoS3AsphaltBasel2.jpg",
          				"tif":"dLC-BichronoS3AsphaltBasel2009.zip",
          				"jpg":"Wi-BichronoS3AsphaltBasel2.jpg"
					},
					{
		        		"thumb":"xssBichrono-SII-BASEL2006.jpg",
          				"tif":"dLC-Bichrono-SII-BASEL2006.zip",
          				"jpg":"Wi-lBichrono-SII-BASEL2006.jpg"
					},
					{
						"thumb":"xssBichrono-deLaCour.jpg",
          				"tif":"dLC-Bichrono-deLaCourRGB.zip",
          				"jpg":"Wi-Bichrono-deLaCour.jpg"
					},
					{
	        			"thumb":"xss120701-02BichronoBasel2.jpg",
          				"tif":"dLC-02BichronoBasel2003RGB.zip",
          				"jpg":"Wi-120701-02BichronoBasel2.jpg"
					},
					{
		        		"thumb":"xss02BichronoHommageDial.jpg",
          				"tif":"dLC-BichronoHommageDial02.zip",
          				"jpg":"Wi-02BichronoHommageDial.jpg"
					},
					{
						"thumb":"xss01BichronoHommageDial.jpg",
          				"tif":"dLC-BichronoHommageDial01-RGB.zip",
          				"jpg":"Wi-01BichronoHommageDial.jpg"
					}
				],

				"texts":[
					{
						"language":"EN",
						"zip":"dLC-Bichrono_Tech-Press_Release-EN_txt.zip"
					}
				]

			}
		]
	}
}